{
  "1": {
    "price": 200,
    "description": "Espresso",
    "imagePath": "../images/coffee-drinks_espresso.webp"
  },
  "2": {
    "price": 250,
    "description": "Americano",
    "imagePath": "../images/coffee-drinks_americano.webp"
  },
  "3": {
    "price": 300,
    "description": "Breve",
    "imagePath": "../images/coffee-drinks_breve.webp"
  },
  "4": {
    "price": 350,
    "description": "Caffe Latte",
    "imagePath": "../images/coffee-drinks_caffe-latte.webp"
  },
  "5": {
    "price": 300,
    "description": "Cappuccino",
    "imagePath": "../images/coffee-drinks_cappuccino.webp"
  },
  "6": {
    "price": 280,
    "description": "Cortado",
    "imagePath": "../images/coffee-drinks_cortado.webp"
  },
  "7": {
    "price": 320,
    "description": "Double Espresso",
    "imagePath": "../images/coffee-drinks_double-espresso.webp"
  },
  "8": {
    "price": 300,
    "description": "Flat White",
    "imagePath": "../images/coffee-drinks_flat-white.webp"
  },
  "9": {
    "price": 270,
    "description": "Macchiato",
    "imagePath": "../images/coffee-drinks_macchiato.webp"
  }
}
